gcs_convert_csv_to_parquet/__init__.py
gcs_convert_csv_to_parquet/main.py
gcs_convert_csv_to_parquet-0.0.dist-info/METADATA
gcs_convert_csv_to_parquet-0.0.dist-info/WHEEL
gcs_convert_csv_to_parquet-0.0.dist-info/entry_points.txt
gcs_convert_csv_to_parquet-0.0.dist-info/top_level.txt
gcs_convert_csv_to_parquet-0.0.dist-info/RECORD
