Metadata-Version: 2.1
Name: gcs-convert-csv-to-parquet
Version: 0.0
